diffgetr/__init__.py
diffgetr/diff_get.py
diffgetr/tests/__init__.py
diffgetr/tests/test_diff_get.py
diffgetr-0.2.1.dist-info/METADATA
diffgetr-0.2.1.dist-info/WHEEL
diffgetr-0.2.1.dist-info/entry_points.txt
diffgetr-0.2.1.dist-info/top_level.txt
diffgetr-0.2.1.dist-info/RECORD
