Metadata-Version: 2.4
Name: diffgetr
Version: 0.2.1
Summary: A Python library for comparing nested data structures with detailed diff reporting and interactive navigation.
Author-email: Your Name <your.email@example.com>
License-Expression: MIT
Project-URL: Homepage, https://github.com/yourusername/diffgetr
Requires-Python: >=3.7
Requires-Dist: deepdiff>=6.0.0
Provides-Extra: dev
Requires-Dist: black>=22.0.0; extra == "dev"
Requires-Dist: build>=0.8.0; extra == "dev"
Requires-Dist: toml>=0.10.0; extra == "dev"
Requires-Dist: requests>=2.25.0; extra == "dev"
